{
  "meta": {
    "generated_at": "2026-06-21T22:07:37.401674+00:00",
    "n_simulations": 10000,
    "pipeline_sec": 10.85,
    "odds_available": true,
    "value_threshold": 0.05
  },
  "group_standings": {
    "A": [
      {
        "team_id": "MEX",
        "team_name": "Mexico",
        "elo": 1818.1513671875,
        "confederation": "CONCACAF",
        "advance_prob": 0.753,
        "avg_points": 5.61,
        "finish_1st": 0.457,
        "finish_2nd": 0.296,
        "finish_3rd": 0.214,
        "finish_4th": 0.033
      },
      {
        "team_id": "KOR",
        "team_name": "Korea Republic",
        "elo": 1828.8486328125,
        "confederation": "AFC",
        "advance_prob": 0.62,
        "avg_points": 4.73,
        "finish_1st": 0.326,
        "finish_2nd": 0.294,
        "finish_3rd": 0.217,
        "finish_4th": 0.163
      },
      {
        "team_id": "CZE",
        "team_name": "Czechia",
        "elo": 1840.654541015625,
        "confederation": "UEFA",
        "advance_prob": 0.514,
        "avg_points": 3.85,
        "finish_1st": 0.214,
        "finish_2nd": 0.3,
        "finish_3rd": 0.343,
        "finish_4th": 0.143
      },
      {
        "team_id": "RSA",
        "team_name": "South Africa",
        "elo": 1656.345458984375,
        "confederation": "CAF",
        "advance_prob": 0.113,
        "avg_points": 1.85,
        "finish_1st": 0.003,
        "finish_2nd": 0.11,
        "finish_3rd": 0.226,
        "finish_4th": 0.661
      }
    ],
    "B": [
      {
        "team_id": "SUI",
        "team_name": "Switzerland",
        "elo": 1959.5574951171875,
        "confederation": "UEFA",
        "advance_prob": 0.963,
        "avg_points": 7.54,
        "finish_1st": 0.778,
        "finish_2nd": 0.185,
        "finish_3rd": 0.031,
        "finish_4th": 0.006
      },
      {
        "team_id": "CAN",
        "team_name": "Canada",
        "elo": 1749.9078369140625,
        "confederation": "CONCACAF",
        "advance_prob": 0.788,
        "avg_points": 4.74,
        "finish_1st": 0.211,
        "finish_2nd": 0.578,
        "finish_3rd": 0.212,
        "finish_4th": 0.0
      },
      {
        "team_id": "BIH",
        "team_name": "Bosnia & Herzegovina",
        "elo": 1740.53466796875,
        "confederation": "UEFA",
        "advance_prob": 0.203,
        "avg_points": 2.85,
        "finish_1st": 0.0,
        "finish_2nd": 0.203,
        "finish_3rd": 0.52,
        "finish_4th": 0.276
      },
      {
        "team_id": "QAT",
        "team_name": "Qatar",
        "elo": 1591.4698486328125,
        "confederation": "AFC",
        "advance_prob": 0.045,
        "avg_points": 1.35,
        "finish_1st": 0.012,
        "finish_2nd": 0.034,
        "finish_3rd": 0.237,
        "finish_4th": 0.718
      }
    ],
    "C": [
      {
        "team_id": "BRA",
        "team_name": "Brazil",
        "elo": 2053.518798828125,
        "confederation": "CONMEBOL",
        "advance_prob": 0.865,
        "avg_points": 6.06,
        "finish_1st": 0.572,
        "finish_2nd": 0.293,
        "finish_3rd": 0.135,
        "finish_4th": 0.0
      },
      {
        "team_id": "MAR",
        "team_name": "Morocco",
        "elo": 1884.677734375,
        "confederation": "CAF",
        "advance_prob": 0.652,
        "avg_points": 4.96,
        "finish_1st": 0.247,
        "finish_2nd": 0.406,
        "finish_3rd": 0.286,
        "finish_4th": 0.061
      },
      {
        "team_id": "SCO",
        "team_name": "Scotland",
        "elo": 1846.322265625,
        "confederation": "UEFA",
        "advance_prob": 0.454,
        "avg_points": 4.34,
        "finish_1st": 0.178,
        "finish_2nd": 0.276,
        "finish_3rd": 0.428,
        "finish_4th": 0.118
      },
      {
        "team_id": "HAI",
        "team_name": "Haiti",
        "elo": 1529.4810791015625,
        "confederation": "CONCACAF",
        "advance_prob": 0.029,
        "avg_points": 0.94,
        "finish_1st": 0.004,
        "finish_2nd": 0.026,
        "finish_3rd": 0.151,
        "finish_4th": 0.82
      }
    ],
    "D": [
      {
        "team_id": "USA",
        "team_name": "USA",
        "elo": 1818.75830078125,
        "confederation": "CONCACAF",
        "advance_prob": 0.983,
        "avg_points": 7.43,
        "finish_1st": 0.861,
        "finish_2nd": 0.123,
        "finish_3rd": 0.017,
        "finish_4th": 0.0
      },
      {
        "team_id": "PAR",
        "team_name": "Paraguay",
        "elo": 1721.357421875,
        "confederation": "CONMEBOL",
        "advance_prob": 0.501,
        "avg_points": 4.3,
        "finish_1st": 0.048,
        "finish_2nd": 0.453,
        "finish_3rd": 0.364,
        "finish_4th": 0.135
      },
      {
        "team_id": "AUS",
        "team_name": "Australia",
        "elo": 1742.24169921875,
        "confederation": "AFC",
        "advance_prob": 0.269,
        "avg_points": 2.62,
        "finish_1st": 0.021,
        "finish_2nd": 0.248,
        "finish_3rd": 0.271,
        "finish_4th": 0.461
      },
      {
        "team_id": "TUR",
        "team_name": "T\u00fcrkiye",
        "elo": 1799.642578125,
        "confederation": "UEFA",
        "advance_prob": 0.247,
        "avg_points": 2.91,
        "finish_1st": 0.07,
        "finish_2nd": 0.177,
        "finish_3rd": 0.348,
        "finish_4th": 0.405
      }
    ],
    "E": [
      {
        "team_id": "GER",
        "team_name": "Germany",
        "elo": 1994.513427734375,
        "confederation": "UEFA",
        "advance_prob": 1.0,
        "avg_points": 7.99,
        "finish_1st": 0.881,
        "finish_2nd": 0.119,
        "finish_3rd": 0.0,
        "finish_4th": 0.0
      },
      {
        "team_id": "ECU",
        "team_name": "Ecuador",
        "elo": 1807.465576171875,
        "confederation": "CONMEBOL",
        "advance_prob": 0.493,
        "avg_points": 3.38,
        "finish_1st": 0.095,
        "finish_2nd": 0.398,
        "finish_3rd": 0.349,
        "finish_4th": 0.158
      },
      {
        "team_id": "CIV",
        "team_name": "C\u00f4te d'Ivoire",
        "elo": 1744.486572265625,
        "confederation": "CAF",
        "advance_prob": 0.39,
        "avg_points": 3.33,
        "finish_1st": 0.024,
        "finish_2nd": 0.366,
        "finish_3rd": 0.386,
        "finish_4th": 0.225
      },
      {
        "team_id": "CUW",
        "team_name": "Cura\u00e7ao",
        "elo": 1514.534423828125,
        "confederation": "CONCACAF",
        "advance_prob": 0.117,
        "avg_points": 1.71,
        "finish_1st": 0.0,
        "finish_2nd": 0.117,
        "finish_3rd": 0.265,
        "finish_4th": 0.617
      }
    ],
    "F": [
      {
        "team_id": "NED",
        "team_name": "Netherlands",
        "elo": 2003.390869140625,
        "confederation": "UEFA",
        "advance_prob": 0.93,
        "avg_points": 6.2,
        "finish_1st": 0.672,
        "finish_2nd": 0.258,
        "finish_3rd": 0.07,
        "finish_4th": 0.0
      },
      {
        "team_id": "SWE",
        "team_name": "Sweden",
        "elo": 1877.609130859375,
        "confederation": "UEFA",
        "advance_prob": 0.505,
        "avg_points": 4.4,
        "finish_1st": 0.117,
        "finish_2nd": 0.388,
        "finish_3rd": 0.408,
        "finish_4th": 0.087
      },
      {
        "team_id": "JPN",
        "team_name": "Japan",
        "elo": 1873.3487548828125,
        "confederation": "AFC",
        "advance_prob": 0.494,
        "avg_points": 4.14,
        "finish_1st": 0.175,
        "finish_2nd": 0.319,
        "finish_3rd": 0.316,
        "finish_4th": 0.19
      },
      {
        "team_id": "TUN",
        "team_name": "Tunisia",
        "elo": 1746.6512451171875,
        "confederation": "CAF",
        "advance_prob": 0.071,
        "avg_points": 1.61,
        "finish_1st": 0.036,
        "finish_2nd": 0.035,
        "finish_3rd": 0.206,
        "finish_4th": 0.723
      }
    ],
    "G": [
      {
        "team_id": "BEL",
        "team_name": "Belgium",
        "elo": 1947.6461181640625,
        "confederation": "UEFA",
        "advance_prob": 0.814,
        "avg_points": 4.44,
        "finish_1st": 0.388,
        "finish_2nd": 0.427,
        "finish_3rd": 0.12,
        "finish_4th": 0.065
      },
      {
        "team_id": "IRN",
        "team_name": "IR Iran",
        "elo": 1814.3538818359375,
        "confederation": "AFC",
        "advance_prob": 0.526,
        "avg_points": 3.69,
        "finish_1st": 0.278,
        "finish_2nd": 0.248,
        "finish_3rd": 0.353,
        "finish_4th": 0.121
      },
      {
        "team_id": "EGY",
        "team_name": "Egypt",
        "elo": 1721.6346435546875,
        "confederation": "CAF",
        "advance_prob": 0.455,
        "avg_points": 3.92,
        "finish_1st": 0.271,
        "finish_2nd": 0.184,
        "finish_3rd": 0.309,
        "finish_4th": 0.235
      },
      {
        "team_id": "NZL",
        "team_name": "New Zealand",
        "elo": 1588.244384765625,
        "confederation": "OFC",
        "advance_prob": 0.204,
        "avg_points": 2.38,
        "finish_1st": 0.063,
        "finish_2nd": 0.141,
        "finish_3rd": 0.218,
        "finish_4th": 0.579
      }
    ],
    "H": [
      {
        "team_id": "ESP",
        "team_name": "Spain",
        "elo": 2052.227783203125,
        "confederation": "UEFA",
        "advance_prob": 0.909,
        "avg_points": 5.89,
        "finish_1st": 0.607,
        "finish_2nd": 0.302,
        "finish_3rd": 0.09,
        "finish_4th": 0.001
      },
      {
        "team_id": "URU",
        "team_name": "Uruguay",
        "elo": 1894.344970703125,
        "confederation": "CONMEBOL",
        "advance_prob": 0.66,
        "avg_points": 5.05,
        "finish_1st": 0.303,
        "finish_2nd": 0.357,
        "finish_3rd": 0.228,
        "finish_4th": 0.112
      },
      {
        "team_id": "CPV",
        "team_name": "Cabo Verde",
        "elo": 1664.044921875,
        "confederation": "CAF",
        "advance_prob": 0.262,
        "avg_points": 2.9,
        "finish_1st": 0.056,
        "finish_2nd": 0.206,
        "finish_3rd": 0.345,
        "finish_4th": 0.393
      },
      {
        "team_id": "SAU",
        "team_name": "Saudi Arabia",
        "elo": 1716.772216796875,
        "confederation": "AFC",
        "advance_prob": 0.169,
        "avg_points": 2.36,
        "finish_1st": 0.034,
        "finish_2nd": 0.135,
        "finish_3rd": 0.337,
        "finish_4th": 0.494
      }
    ],
    "I": [
      {
        "team_id": "FRA",
        "team_name": "France",
        "elo": 2015.117919921875,
        "confederation": "UEFA",
        "advance_prob": 0.935,
        "avg_points": 7.11,
        "finish_1st": 0.672,
        "finish_2nd": 0.264,
        "finish_3rd": 0.053,
        "finish_4th": 0.011
      },
      {
        "team_id": "NOR",
        "team_name": "Norway",
        "elo": 1926.5302734375,
        "confederation": "UEFA",
        "advance_prob": 0.647,
        "avg_points": 4.98,
        "finish_1st": 0.266,
        "finish_2nd": 0.382,
        "finish_3rd": 0.248,
        "finish_4th": 0.105
      },
      {
        "team_id": "SEN",
        "team_name": "Senegal",
        "elo": 1860.882080078125,
        "confederation": "CAF",
        "advance_prob": 0.296,
        "avg_points": 3.26,
        "finish_1st": 0.038,
        "finish_2nd": 0.258,
        "finish_3rd": 0.457,
        "finish_4th": 0.246
      },
      {
        "team_id": "IRQ",
        "team_name": "Iraq",
        "elo": 1643.4697265625,
        "confederation": "AFC",
        "advance_prob": 0.121,
        "avg_points": 1.72,
        "finish_1st": 0.025,
        "finish_2nd": 0.097,
        "finish_3rd": 0.242,
        "finish_4th": 0.637
      }
    ],
    "J": [
      {
        "team_id": "ARG",
        "team_name": "Argentina",
        "elo": 2144.541748046875,
        "confederation": "CONMEBOL",
        "advance_prob": 0.977,
        "avg_points": 7.89,
        "finish_1st": 0.802,
        "finish_2nd": 0.175,
        "finish_3rd": 0.021,
        "finish_4th": 0.001
      },
      {
        "team_id": "AUT",
        "team_name": "Austria",
        "elo": 1878.035888671875,
        "confederation": "UEFA",
        "advance_prob": 0.732,
        "avg_points": 5.3,
        "finish_1st": 0.18,
        "finish_2nd": 0.552,
        "finish_3rd": 0.248,
        "finish_4th": 0.02
      },
      {
        "team_id": "ALG",
        "team_name": "Algeria",
        "elo": 1775.4583740234375,
        "confederation": "CAF",
        "advance_prob": 0.254,
        "avg_points": 2.91,
        "finish_1st": 0.014,
        "finish_2nd": 0.241,
        "finish_3rd": 0.46,
        "finish_4th": 0.286
      },
      {
        "team_id": "JOR",
        "team_name": "Jordan",
        "elo": 1643.964111328125,
        "confederation": "AFC",
        "advance_prob": 0.036,
        "avg_points": 1.19,
        "finish_1st": 0.004,
        "finish_2nd": 0.033,
        "finish_3rd": 0.271,
        "finish_4th": 0.693
      }
    ],
    "K": [
      {
        "team_id": "POR",
        "team_name": "Portugal",
        "elo": 2000.123291015625,
        "confederation": "UEFA",
        "advance_prob": 0.773,
        "avg_points": 5.16,
        "finish_1st": 0.43,
        "finish_2nd": 0.343,
        "finish_3rd": 0.181,
        "finish_4th": 0.045
      },
      {
        "team_id": "COL",
        "team_name": "Colombia",
        "elo": 1916.5999755859375,
        "confederation": "CONMEBOL",
        "advance_prob": 0.738,
        "avg_points": 5.59,
        "finish_1st": 0.427,
        "finish_2nd": 0.311,
        "finish_3rd": 0.187,
        "finish_4th": 0.075
      },
      {
        "team_id": "COD",
        "team_name": "Congo DR",
        "elo": 1691.876708984375,
        "confederation": "CAF",
        "advance_prob": 0.349,
        "avg_points": 3.38,
        "finish_1st": 0.098,
        "finish_2nd": 0.252,
        "finish_3rd": 0.382,
        "finish_4th": 0.269
      },
      {
        "team_id": "UZB",
        "team_name": "Uzbekistan",
        "elo": 1597.4000244140625,
        "confederation": "AFC",
        "advance_prob": 0.139,
        "avg_points": 1.97,
        "finish_1st": 0.045,
        "finish_2nd": 0.094,
        "finish_3rd": 0.249,
        "finish_4th": 0.612
      }
    ],
    "L": [
      {
        "team_id": "ENG",
        "team_name": "England",
        "elo": 2003.713134765625,
        "confederation": "UEFA",
        "advance_prob": 0.961,
        "avg_points": 7.67,
        "finish_1st": 0.835,
        "finish_2nd": 0.125,
        "finish_3rd": 0.033,
        "finish_4th": 0.007
      },
      {
        "team_id": "CRO",
        "team_name": "Croatia",
        "elo": 1926.286865234375,
        "confederation": "UEFA",
        "advance_prob": 0.578,
        "avg_points": 4.28,
        "finish_1st": 0.058,
        "finish_2nd": 0.52,
        "finish_3rd": 0.286,
        "finish_4th": 0.136
      },
      {
        "team_id": "GHA",
        "team_name": "Ghana",
        "elo": 1701.598388671875,
        "confederation": "CAF",
        "advance_prob": 0.251,
        "avg_points": 2.7,
        "finish_1st": 0.06,
        "finish_2nd": 0.191,
        "finish_3rd": 0.345,
        "finish_4th": 0.404
      },
      {
        "team_id": "PAN",
        "team_name": "Panama",
        "elo": 1681.401611328125,
        "confederation": "CONCACAF",
        "advance_prob": 0.21,
        "avg_points": 2.45,
        "finish_1st": 0.047,
        "finish_2nd": 0.163,
        "finish_3rd": 0.337,
        "finish_4th": 0.453
      }
    ]
  },
  "group_fixtures": {
    "A": [
      {
        "id": 1,
        "group": "A",
        "round": 1,
        "date": "2026-06-11",
        "home": "MEX",
        "away": "RSA",
        "home_name": "Mexico",
        "away_name": "South Africa",
        "status": "finished",
        "home_score": 2,
        "away_score": 0,
        "elo_home": 1818.1513671875,
        "elo_away": 1656.345458984375,
        "model": null,
        "confidence": 0,
        "n_observations": 0
      },
      {
        "id": 2,
        "group": "A",
        "round": 1,
        "date": "2026-06-11",
        "home": "KOR",
        "away": "CZE",
        "home_name": "Korea Republic",
        "away_name": "Czechia",
        "status": "finished",
        "home_score": 2,
        "away_score": 1,
        "elo_home": 1828.8486328125,
        "elo_away": 1840.654541015625,
        "model": null,
        "confidence": 0,
        "n_observations": 0
      },
      {
        "id": 25,
        "group": "A",
        "round": 2,
        "date": "2026-06-18",
        "home": "CZE",
        "away": "RSA",
        "home_name": "Czechia",
        "away_name": "South Africa",
        "status": "finished",
        "home_score": 1,
        "away_score": 1,
        "elo_home": 1840.654541015625,
        "elo_away": 1656.345458984375,
        "model": null,
        "confidence": 0,
        "n_observations": 0
      },
      {
        "id": 28,
        "group": "A",
        "round": 2,
        "date": "2026-06-18",
        "home": "MEX",
        "away": "KOR",
        "home_name": "Mexico",
        "away_name": "Korea Republic",
        "status": "finished",
        "home_score": 1,
        "away_score": 0,
        "elo_home": 1818.1513671875,
        "elo_away": 1828.8486328125,
        "model": null,
        "confidence": 0,
        "n_observations": 0
      },
      {
        "id": 53,
        "group": "A",
        "round": 3,
        "date": "2026-06-24",
        "home": "CZE",
        "away": "MEX",
        "home_name": "Czechia",
        "away_name": "Mexico",
        "status": "scheduled",
        "home_score": null,
        "away_score": null,
        "elo_home": 1840.654541015625,
        "elo_away": 1818.1513671875,
        "model": {
          "home_win": 0.265,
          "draw": 0.2547,
          "away_win": 0.4803
        },
        "confidence": 0.9835,
        "n_observations": 2878
      },
      {
        "id": 54,
        "group": "A",
        "round": 3,
        "date": "2026-06-24",
        "home": "RSA",
        "away": "KOR",
        "home_name": "South Africa",
        "away_name": "Korea Republic",
        "status": "scheduled",
        "home_score": null,
        "away_score": null,
        "elo_home": 1656.345458984375,
        "elo_away": 1828.8486328125,
        "model": {
          "home_win": 0.1674,
          "draw": 0.241,
          "away_win": 0.5916
        },
        "confidence": 0.9836,
        "n_observations": 2867
      }
    ],
    "B": [
      {
        "id": 3,
        "group": "B",
        "round": 1,
        "date": "2026-06-12",
        "home": "CAN",
        "away": "BIH",
        "home_name": "Canada",
        "away_name": "Bosnia & Herzegovina",
        "status": "finished",
        "home_score": 1,
        "away_score": 1,
        "elo_home": 1749.9078369140625,
        "elo_away": 1740.53466796875,
        "model": null,
        "confidence": 0,
        "n_observations": 0
      },
      {
        "id": 8,
        "group": "B",
        "round": 1,
        "date": "2026-06-13",
        "home": "QAT",
        "away": "SUI",
        "home_name": "Qatar",
        "away_name": "Switzerland",
        "status": "finished",
        "home_score": 1,
        "away_score": 1,
        "elo_home": 1591.4698486328125,
        "elo_away": 1959.5574951171875,
        "model": null,
        "confidence": 0,
        "n_observations": 0
      },
      {
        "id": 26,
        "group": "B",
        "round": 2,
        "date": "2026-06-18",
        "home": "SUI",
        "away": "BIH",
        "home_name": "Switzerland",
        "away_name": "Bosnia & Herzegovina",
        "status": "finished",
        "home_score": 4,
        "away_score": 1,
        "elo_home": 1959.5574951171875,
        "elo_away": 1740.53466796875,
        "model": null,
        "confidence": 0,
        "n_observations": 0
      },
      {
        "id": 27,
        "group": "B",
        "round": 2,
        "date": "2026-06-18",
        "home": "CAN",
        "away": "QAT",
        "home_name": "Canada",
        "away_name": "Qatar",
        "status": "finished",
        "home_score": 6,
        "away_score": 0,
        "elo_home": 1749.9078369140625,
        "elo_away": 1591.4698486328125,
        "model": null,
        "confidence": 0,
        "n_observations": 0
      },
      {
        "id": 51,
        "group": "B",
        "round": 3,
        "date": "2026-06-24",
        "home": "SUI",
        "away": "CAN",
        "home_name": "Switzerland",
        "away_name": "Canada",
        "status": "scheduled",
        "home_score": null,
        "away_score": null,
        "elo_home": 1959.5574951171875,
        "elo_away": 1749.9078369140625,
        "model": {
          "home_win": 0.3951,
          "draw": 0.3068,
          "away_win": 0.298
        },
        "confidence": 0.9837,
        "n_observations": 3128
      },
      {
        "id": 52,
        "group": "B",
        "round": 3,
        "date": "2026-06-24",
        "home": "BIH",
        "away": "QAT",
        "home_name": "Bosnia & Herzegovina",
        "away_name": "Qatar",
        "status": "scheduled",
        "home_score": null,
        "away_score": null,
        "elo_home": 1740.53466796875,
        "elo_away": 1591.4698486328125,
        "model": {
          "home_win": 0.6659,
          "draw": 0.1958,
          "away_win": 0.1383
        },
        "confidence": 0.9837,
        "n_observations": 3134
      }
    ],
    "D": [
      {
        "id": 4,
        "group": "D",
        "round": 1,
        "date": "2026-06-12",
        "home": "USA",
        "away": "PAR",
        "home_name": "USA",
        "away_name": "Paraguay",
        "status": "finished",
        "home_score": 4,
        "away_score": 1,
        "elo_home": 1818.75830078125,
        "elo_away": 1721.357421875,
        "model": null,
        "confidence": 0,
        "n_observations": 0
      },
      {
        "id": 6,
        "group": "D",
        "round": 1,
        "date": "2026-06-13",
        "home": "AUS",
        "away": "TUR",
        "home_name": "Australia",
        "away_name": "T\u00fcrkiye",
        "status": "finished",
        "home_score": 2,
        "away_score": 0,
        "elo_home": 1742.24169921875,
        "elo_away": 1799.642578125,
        "model": null,
        "confidence": 0,
        "n_observations": 0
      },
      {
        "id": 31,
        "group": "D",
        "round": 2,
        "date": "2026-06-19",
        "home": "TUR",
        "away": "PAR",
        "home_name": "T\u00fcrkiye",
        "away_name": "Paraguay",
        "status": "finished",
        "home_score": 0,
        "away_score": 1,
        "elo_home": 1799.642578125,
        "elo_away": 1721.357421875,
        "model": null,
        "confidence": 0,
        "n_observations": 0
      },
      {
        "id": 32,
        "group": "D",
        "round": 2,
        "date": "2026-06-19",
        "home": "USA",
        "away": "AUS",
        "home_name": "USA",
        "away_name": "Australia",
        "status": "finished",
        "home_score": 2,
        "away_score": 0,
        "elo_home": 1818.75830078125,
        "elo_away": 1742.24169921875,
        "model": null,
        "confidence": 0,
        "n_observations": 0
      },
      {
        "id": 59,
        "group": "D",
        "round": 3,
        "date": "2026-06-25",
        "home": "TUR",
        "away": "USA",
        "home_name": "T\u00fcrkiye",
        "away_name": "USA",
        "status": "scheduled",
        "home_score": null,
        "away_score": null,
        "elo_home": 1799.642578125,
        "elo_away": 1818.75830078125,
        "model": {
          "home_win": 0.3006,
          "draw": 0.2397,
          "away_win": 0.4597
        },
        "confidence": 0.9823,
        "n_observations": 2734
      },
      {
        "id": 60,
        "group": "D",
        "round": 3,
        "date": "2026-06-25",
        "home": "PAR",
        "away": "AUS",
        "home_name": "Paraguay",
        "away_name": "Australia",
        "status": "scheduled",
        "home_score": null,
        "away_score": null,
        "elo_home": 1721.357421875,
        "elo_away": 1742.24169921875,
        "model": {
          "home_win": 0.3425,
          "draw": 0.4075,
          "away_win": 0.25
        },
        "confidence": 0.9821,
        "n_observations": 2869
      }
    ],
    "C": [
      {
        "id": 5,
        "group": "C",
        "round": 1,
        "date": "2026-06-13",
        "home": "HAI",
        "away": "SCO",
        "home_name": "Haiti",
        "away_name": "Scotland",
        "status": "finished",
        "home_score": 0,
        "away_score": 1,
        "elo_home": 1529.4810791015625,
        "elo_away": 1846.322265625,
        "model": null,
        "confidence": 0,
        "n_observations": 0
      },
      {
        "id": 7,
        "group": "C",
        "round": 1,
        "date": "2026-06-13",
        "home": "BRA",
        "away": "MAR",
        "home_name": "Brazil",
        "away_name": "Morocco",
        "status": "finished",
        "home_score": 1,
        "away_score": 1,
        "elo_home": 2053.518798828125,
        "elo_away": 1884.677734375,
        "model": null,
        "confidence": 0,
        "n_observations": 0
      },
      {
        "id": 29,
        "group": "C",
        "round": 2,
        "date": "2026-06-19",
        "home": "BRA",
        "away": "HAI",
        "home_name": "Brazil",
        "away_name": "Haiti",
        "status": "finished",
        "home_score": 3,
        "away_score": 0,
        "elo_home": 2053.518798828125,
        "elo_away": 1529.4810791015625,
        "model": null,
        "confidence": 0,
        "n_observations": 0
      },
      {
        "id": 30,
        "group": "C",
        "round": 2,
        "date": "2026-06-19",
        "home": "SCO",
        "away": "MAR",
        "home_name": "Scotland",
        "away_name": "Morocco",
        "status": "finished",
        "home_score": 0,
        "away_score": 1,
        "elo_home": 1846.322265625,
        "elo_away": 1884.677734375,
        "model": null,
        "confidence": 0,
        "n_observations": 0
      },
      {
        "id": 49,
        "group": "C",
        "round": 3,
        "date": "2026-06-24",
        "home": "SCO",
        "away": "BRA",
        "home_name": "Scotland",
        "away_name": "Brazil",
        "status": "scheduled",
        "home_score": null,
        "away_score": null,
        "elo_home": 1846.322265625,
        "elo_away": 2053.518798828125,
        "model": {
          "home_win": 0.1263,
          "draw": 0.1861,
          "away_win": 0.6876
        },
        "confidence": 0.9836,
        "n_observations": 3057
      },
      {
        "id": 50,
        "group": "C",
        "round": 3,
        "date": "2026-06-24",
        "home": "MAR",
        "away": "HAI",
        "home_name": "Morocco",
        "away_name": "Haiti",
        "status": "scheduled",
        "home_score": null,
        "away_score": null,
        "elo_home": 1884.677734375,
        "elo_away": 1529.4810791015625,
        "model": {
          "home_win": 0.7969,
          "draw": 0.1401,
          "away_win": 0.063
        },
        "confidence": 0.9836,
        "n_observations": 3076
      }
    ],
    "E": [
      {
        "id": 9,
        "group": "E",
        "round": 1,
        "date": "2026-06-14",
        "home": "CIV",
        "away": "ECU",
        "home_name": "C\u00f4te d'Ivoire",
        "away_name": "Ecuador",
        "status": "finished",
        "home_score": 1,
        "away_score": 0,
        "elo_home": 1744.486572265625,
        "elo_away": 1807.465576171875,
        "model": null,
        "confidence": 0,
        "n_observations": 0
      },
      {
        "id": 10,
        "group": "E",
        "round": 1,
        "date": "2026-06-14",
        "home": "GER",
        "away": "CUW",
        "home_name": "Germany",
        "away_name": "Cura\u00e7ao",
        "status": "finished",
        "home_score": 7,
        "away_score": 1,
        "elo_home": 1994.513427734375,
        "elo_away": 1514.534423828125,
        "model": null,
        "confidence": 0,
        "n_observations": 0
      },
      {
        "id": 33,
        "group": "E",
        "round": 2,
        "date": "2026-06-20",
        "home": "GER",
        "away": "CIV",
        "home_name": "Germany",
        "away_name": "C\u00f4te d'Ivoire",
        "status": "finished",
        "home_score": 2,
        "away_score": 1,
        "elo_home": 1994.513427734375,
        "elo_away": 1744.486572265625,
        "model": null,
        "confidence": 0,
        "n_observations": 0
      },
      {
        "id": 34,
        "group": "E",
        "round": 2,
        "date": "2026-06-20",
        "home": "ECU",
        "away": "CUW",
        "home_name": "Ecuador",
        "away_name": "Cura\u00e7ao",
        "status": "finished",
        "home_score": 0,
        "away_score": 0,
        "elo_home": 1807.465576171875,
        "elo_away": 1514.534423828125,
        "model": null,
        "confidence": 0,
        "n_observations": 0
      },
      {
        "id": 55,
        "group": "E",
        "round": 3,
        "date": "2026-06-25",
        "home": "CUW",
        "away": "CIV",
        "home_name": "Cura\u00e7ao",
        "away_name": "C\u00f4te d'Ivoire",
        "status": "scheduled",
        "home_score": null,
        "away_score": null,
        "elo_home": 1514.534423828125,
        "elo_away": 1744.486572265625,
        "model": {
          "home_win": 0.0533,
          "draw": 0.1126,
          "away_win": 0.834
        },
        "confidence": 0.9823,
        "n_observations": 2779
      },
      {
        "id": 56,
        "group": "E",
        "round": 3,
        "date": "2026-06-25",
        "home": "ECU",
        "away": "GER",
        "home_name": "Ecuador",
        "away_name": "Germany",
        "status": "scheduled",
        "home_score": null,
        "away_score": null,
        "elo_home": 1807.465576171875,
        "elo_away": 1994.513427734375,
        "model": {
          "home_win": 0.2445,
          "draw": 0.2508,
          "away_win": 0.5047
        },
        "confidence": 0.9822,
        "n_observations": 2904
      }
    ],
    "F": [
      {
        "id": 11,
        "group": "F",
        "round": 1,
        "date": "2026-06-14",
        "home": "NED",
        "away": "JPN",
        "home_name": "Netherlands",
        "away_name": "Japan",
        "status": "finished",
        "home_score": 2,
        "away_score": 2,
        "elo_home": 2003.390869140625,
        "elo_away": 1873.3487548828125,
        "model": null,
        "confidence": 0,
        "n_observations": 0
      },
      {
        "id": 12,
        "group": "F",
        "round": 1,
        "date": "2026-06-14",
        "home": "SWE",
        "away": "TUN",
        "home_name": "Sweden",
        "away_name": "Tunisia",
        "status": "finished",
        "home_score": 5,
        "away_score": 1,
        "elo_home": 1877.609130859375,
        "elo_away": 1746.6512451171875,
        "model": null,
        "confidence": 0,
        "n_observations": 0
      },
      {
        "id": 35,
        "group": "F",
        "round": 2,
        "date": "2026-06-20",
        "home": "NED",
        "away": "SWE",
        "home_name": "Netherlands",
        "away_name": "Sweden",
        "status": "finished",
        "home_score": 5,
        "away_score": 1,
        "elo_home": 2003.390869140625,
        "elo_away": 1877.609130859375,
        "model": null,
        "confidence": 0,
        "n_observations": 0
      },
      {
        "id": 36,
        "group": "F",
        "round": 2,
        "date": "2026-06-20",
        "home": "TUN",
        "away": "JPN",
        "home_name": "Tunisia",
        "away_name": "Japan",
        "status": "finished",
        "home_score": 0,
        "away_score": 4,
        "elo_home": 1746.6512451171875,
        "elo_away": 1873.3487548828125,
        "model": null,
        "confidence": 0,
        "n_observations": 0
      },
      {
        "id": 57,
        "group": "F",
        "round": 3,
        "date": "2026-06-25",
        "home": "JPN",
        "away": "SWE",
        "home_name": "Japan",
        "away_name": "Sweden",
        "status": "scheduled",
        "home_score": null,
        "away_score": null,
        "elo_home": 1873.3487548828125,
        "elo_away": 1877.609130859375,
        "model": {
          "home_win": 0.4663,
          "draw": 0.2802,
          "away_win": 0.2535
        },
        "confidence": 0.9816,
        "n_observations": 2871
      },
      {
        "id": 58,
        "group": "F",
        "round": 3,
        "date": "2026-06-25",
        "home": "TUN",
        "away": "NED",
        "home_name": "Tunisia",
        "away_name": "Netherlands",
        "status": "scheduled",
        "home_score": null,
        "away_score": null,
        "elo_home": 1746.6512451171875,
        "elo_away": 2003.390869140625,
        "model": {
          "home_win": 0.0696,
          "draw": 0.1388,
          "away_win": 0.7916
        },
        "confidence": 0.9818,
        "n_observations": 2878
      }
    ],
    "H": [
      {
        "id": 13,
        "group": "H",
        "round": 1,
        "date": "2026-06-15",
        "home": "SAU",
        "away": "URU",
        "home_name": "Saudi Arabia",
        "away_name": "Uruguay",
        "status": "finished",
        "home_score": 1,
        "away_score": 1,
        "elo_home": 1716.772216796875,
        "elo_away": 1894.344970703125,
        "model": null,
        "confidence": 0,
        "n_observations": 0
      },
      {
        "id": 14,
        "group": "H",
        "round": 1,
        "date": "2026-06-15",
        "home": "ESP",
        "away": "CPV",
        "home_name": "Spain",
        "away_name": "Cabo Verde",
        "status": "finished",
        "home_score": 0,
        "away_score": 0,
        "elo_home": 2052.227783203125,
        "elo_away": 1664.044921875,
        "model": null,
        "confidence": 0,
        "n_observations": 0
      },
      {
        "id": 37,
        "group": "H",
        "round": 2,
        "date": "2026-06-21",
        "home": "URU",
        "away": "CPV",
        "home_name": "Uruguay",
        "away_name": "Cabo Verde",
        "status": "scheduled",
        "home_score": null,
        "away_score": null,
        "elo_home": 1894.344970703125,
        "elo_away": 1664.044921875,
        "model": {
          "home_win": 0.6748,
          "draw": 0.2182,
          "away_win": 0.107
        },
        "confidence": 0.9483,
        "n_observations": 3370
      },
      {
        "id": 38,
        "group": "H",
        "round": 2,
        "date": "2026-06-21",
        "home": "ESP",
        "away": "SAU",
        "home_name": "Spain",
        "away_name": "Saudi Arabia",
        "status": "finished",
        "home_score": 5,
        "away_score": 0,
        "elo_home": 2052.227783203125,
        "elo_away": 1716.772216796875,
        "model": null,
        "confidence": 0,
        "n_observations": 0
      },
      {
        "id": 65,
        "group": "H",
        "round": 3,
        "date": "2026-06-26",
        "home": "CPV",
        "away": "SAU",
        "home_name": "Cabo Verde",
        "away_name": "Saudi Arabia",
        "status": "scheduled",
        "home_score": null,
        "away_score": null,
        "elo_home": 1664.044921875,
        "elo_away": 1716.772216796875,
        "model": {
          "home_win": 0.3546,
          "draw": 0.2601,
          "away_win": 0.3854
        },
        "confidence": 0.9804,
        "n_observations": 2699
      },
      {
        "id": 66,
        "group": "H",
        "round": 3,
        "date": "2026-06-26",
        "home": "URU",
        "away": "ESP",
        "home_name": "Uruguay",
        "away_name": "Spain",
        "status": "scheduled",
        "home_score": null,
        "away_score": null,
        "elo_home": 1894.344970703125,
        "elo_away": 2052.227783203125,
        "model": {
          "home_win": 0.1593,
          "draw": 0.2258,
          "away_win": 0.6148
        },
        "confidence": 0.9806,
        "n_observations": 2826
      }
    ],
    "G": [
      {
        "id": 15,
        "group": "G",
        "round": 1,
        "date": "2026-06-15",
        "home": "IRN",
        "away": "NZL",
        "home_name": "IR Iran",
        "away_name": "New Zealand",
        "status": "finished",
        "home_score": 2,
        "away_score": 2,
        "elo_home": 1814.3538818359375,
        "elo_away": 1588.244384765625,
        "model": null,
        "confidence": 0,
        "n_observations": 0
      },
      {
        "id": 16,
        "group": "G",
        "round": 1,
        "date": "2026-06-15",
        "home": "BEL",
        "away": "EGY",
        "home_name": "Belgium",
        "away_name": "Egypt",
        "status": "finished",
        "home_score": 1,
        "away_score": 1,
        "elo_home": 1947.6461181640625,
        "elo_away": 1721.6346435546875,
        "model": null,
        "confidence": 0,
        "n_observations": 0
      },
      {
        "id": 39,
        "group": "G",
        "round": 2,
        "date": "2026-06-21",
        "home": "BEL",
        "away": "IRN",
        "home_name": "Belgium",
        "away_name": "IR Iran",
        "status": "finished",
        "home_score": 0,
        "away_score": 0,
        "elo_home": 1947.6461181640625,
        "elo_away": 1814.3538818359375,
        "model": null,
        "confidence": 0,
        "n_observations": 0
      },
      {
        "id": 40,
        "group": "G",
        "round": 2,
        "date": "2026-06-21",
        "home": "NZL",
        "away": "EGY",
        "home_name": "New Zealand",
        "away_name": "Egypt",
        "status": "scheduled",
        "home_score": null,
        "away_score": null,
        "elo_home": 1588.244384765625,
        "elo_away": 1721.6346435546875,
        "model": {
          "home_win": 0.164,
          "draw": 0.2362,
          "away_win": 0.5998
        },
        "confidence": 0.9488,
        "n_observations": 3532
      },
      {
        "id": 63,
        "group": "G",
        "round": 3,
        "date": "2026-06-26",
        "home": "EGY",
        "away": "IRN",
        "home_name": "Egypt",
        "away_name": "IR Iran",
        "status": "scheduled",
        "home_score": null,
        "away_score": null,
        "elo_home": 1721.6346435546875,
        "elo_away": 1814.3538818359375,
        "model": {
          "home_win": 0.4524,
          "draw": 0.3016,
          "away_win": 0.246
        },
        "confidence": 0.9808,
        "n_observations": 2830
      },
      {
        "id": 64,
        "group": "G",
        "round": 3,
        "date": "2026-06-26",
        "home": "NZL",
        "away": "BEL",
        "home_name": "New Zealand",
        "away_name": "Belgium",
        "status": "scheduled",
        "home_score": null,
        "away_score": null,
        "elo_home": 1588.244384765625,
        "elo_away": 1947.6461181640625,
        "model": {
          "home_win": 0.0775,
          "draw": 0.1511,
          "away_win": 0.7714
        },
        "confidence": 0.9806,
        "n_observations": 2827
      }
    ],
    "I": [
      {
        "id": 17,
        "group": "I",
        "round": 1,
        "date": "2026-06-16",
        "home": "FRA",
        "away": "SEN",
        "home_name": "France",
        "away_name": "Senegal",
        "status": "finished",
        "home_score": 3,
        "away_score": 1,
        "elo_home": 2015.117919921875,
        "elo_away": 1860.882080078125,
        "model": null,
        "confidence": 0,
        "n_observations": 0
      },
      {
        "id": 18,
        "group": "I",
        "round": 1,
        "date": "2026-06-16",
        "home": "IRQ",
        "away": "NOR",
        "home_name": "Iraq",
        "away_name": "Norway",
        "status": "finished",
        "home_score": 1,
        "away_score": 4,
        "elo_home": 1643.4697265625,
        "elo_away": 1926.5302734375,
        "model": null,
        "confidence": 0,
        "n_observations": 0
      },
      {
        "id": 41,
        "group": "I",
        "round": 2,
        "date": "2026-06-22",
        "home": "NOR",
        "away": "SEN",
        "home_name": "Norway",
        "away_name": "Senegal",
        "status": "scheduled",
        "home_score": null,
        "away_score": null,
        "elo_home": 1926.5302734375,
        "elo_away": 1860.882080078125,
        "model": {
          "home_win": 0.4195,
          "draw": 0.272,
          "away_win": 0.3084
        },
        "confidence": 0.9488,
        "n_observations": 3498
      },
      {
        "id": 42,
        "group": "I",
        "round": 2,
        "date": "2026-06-22",
        "home": "FRA",
        "away": "IRQ",
        "home_name": "France",
        "away_name": "Iraq",
        "status": "scheduled",
        "home_score": null,
        "away_score": null,
        "elo_home": 2015.117919921875,
        "elo_away": 1643.4697265625,
        "model": {
          "home_win": 0.8783,
          "draw": 0.0857,
          "away_win": 0.036
        },
        "confidence": 0.9488,
        "n_observations": 3485
      },
      {
        "id": 61,
        "group": "I",
        "round": 3,
        "date": "2026-06-26",
        "home": "NOR",
        "away": "FRA",
        "home_name": "Norway",
        "away_name": "France",
        "status": "scheduled",
        "home_score": null,
        "away_score": null,
        "elo_home": 1926.5302734375,
        "elo_away": 2015.117919921875,
        "model": {
          "home_win": 0.2227,
          "draw": 0.2508,
          "away_win": 0.5265
        },
        "confidence": 0.9818,
        "n_observations": 2868
      },
      {
        "id": 62,
        "group": "I",
        "round": 3,
        "date": "2026-06-26",
        "home": "SEN",
        "away": "IRQ",
        "home_name": "Senegal",
        "away_name": "Iraq",
        "status": "scheduled",
        "home_score": null,
        "away_score": null,
        "elo_home": 1860.882080078125,
        "elo_away": 1643.4697265625,
        "model": {
          "home_win": 0.7286,
          "draw": 0.1776,
          "away_win": 0.0938
        },
        "confidence": 0.9818,
        "n_observations": 2859
      }
    ],
    "J": [
      {
        "id": 19,
        "group": "J",
        "round": 1,
        "date": "2026-06-16",
        "home": "ARG",
        "away": "ALG",
        "home_name": "Argentina",
        "away_name": "Algeria",
        "status": "finished",
        "home_score": 3,
        "away_score": 0,
        "elo_home": 2144.541748046875,
        "elo_away": 1775.4583740234375,
        "model": null,
        "confidence": 0,
        "n_observations": 0
      },
      {
        "id": 20,
        "group": "J",
        "round": 1,
        "date": "2026-06-16",
        "home": "AUT",
        "away": "JOR",
        "home_name": "Austria",
        "away_name": "Jordan",
        "status": "finished",
        "home_score": 3,
        "away_score": 1,
        "elo_home": 1878.035888671875,
        "elo_away": 1643.964111328125,
        "model": null,
        "confidence": 0,
        "n_observations": 0
      },
      {
        "id": 43,
        "group": "J",
        "round": 2,
        "date": "2026-06-22",
        "home": "ARG",
        "away": "AUT",
        "home_name": "Argentina",
        "away_name": "Austria",
        "status": "scheduled",
        "home_score": null,
        "away_score": null,
        "elo_home": 2144.541748046875,
        "elo_away": 1878.035888671875,
        "model": {
          "home_win": 0.6299,
          "draw": 0.2283,
          "away_win": 0.1418
        },
        "confidence": 0.9488,
        "n_observations": 3528
      },
      {
        "id": 44,
        "group": "J",
        "round": 2,
        "date": "2026-06-22",
        "home": "JOR",
        "away": "ALG",
        "home_name": "Jordan",
        "away_name": "Algeria",
        "status": "scheduled",
        "home_score": null,
        "away_score": null,
        "elo_home": 1643.964111328125,
        "elo_away": 1775.4583740234375,
        "model": {
          "home_win": 0.1643,
          "draw": 0.2299,
          "away_win": 0.6059
        },
        "confidence": 0.9488,
        "n_observations": 3493
      },
      {
        "id": 69,
        "group": "J",
        "round": 3,
        "date": "2026-06-27",
        "home": "ALG",
        "away": "AUT",
        "home_name": "Algeria",
        "away_name": "Austria",
        "status": "scheduled",
        "home_score": null,
        "away_score": null,
        "elo_home": 1775.4583740234375,
        "elo_away": 1878.035888671875,
        "model": {
          "home_win": 0.3099,
          "draw": 0.3077,
          "away_win": 0.3824
        },
        "confidence": 0.9813,
        "n_observations": 2793
      },
      {
        "id": 70,
        "group": "J",
        "round": 3,
        "date": "2026-06-27",
        "home": "JOR",
        "away": "ARG",
        "home_name": "Jordan",
        "away_name": "Argentina",
        "status": "scheduled",
        "home_score": null,
        "away_score": null,
        "elo_home": 1643.964111328125,
        "elo_away": 2144.541748046875,
        "model": {
          "home_win": 0.0692,
          "draw": 0.1388,
          "away_win": 0.792
        },
        "confidence": 0.9813,
        "n_observations": 2783
      }
    ],
    "L": [
      {
        "id": 21,
        "group": "L",
        "round": 1,
        "date": "2026-06-17",
        "home": "GHA",
        "away": "PAN",
        "home_name": "Ghana",
        "away_name": "Panama",
        "status": "finished",
        "home_score": 1,
        "away_score": 0,
        "elo_home": 1701.598388671875,
        "elo_away": 1681.401611328125,
        "model": null,
        "confidence": 0,
        "n_observations": 0
      },
      {
        "id": 22,
        "group": "L",
        "round": 1,
        "date": "2026-06-17",
        "home": "ENG",
        "away": "CRO",
        "home_name": "England",
        "away_name": "Croatia",
        "status": "finished",
        "home_score": 4,
        "away_score": 2,
        "elo_home": 2003.713134765625,
        "elo_away": 1926.286865234375,
        "model": null,
        "confidence": 0,
        "n_observations": 0
      },
      {
        "id": 45,
        "group": "L",
        "round": 2,
        "date": "2026-06-23",
        "home": "ENG",
        "away": "GHA",
        "home_name": "England",
        "away_name": "Ghana",
        "status": "scheduled",
        "home_score": null,
        "away_score": null,
        "elo_home": 2003.713134765625,
        "elo_away": 1701.598388671875,
        "model": {
          "home_win": 0.7849,
          "draw": 0.1457,
          "away_win": 0.0693
        },
        "confidence": 0.9839,
        "n_observations": 3460
      },
      {
        "id": 46,
        "group": "L",
        "round": 2,
        "date": "2026-06-23",
        "home": "PAN",
        "away": "CRO",
        "home_name": "Panama",
        "away_name": "Croatia",
        "status": "scheduled",
        "home_score": null,
        "away_score": null,
        "elo_home": 1681.401611328125,
        "elo_away": 1926.286865234375,
        "model": {
          "home_win": 0.1427,
          "draw": 0.2372,
          "away_win": 0.6201
        },
        "confidence": 0.9838,
        "n_observations": 3447
      },
      {
        "id": 67,
        "group": "L",
        "round": 3,
        "date": "2026-06-27",
        "home": "PAN",
        "away": "ENG",
        "home_name": "Panama",
        "away_name": "England",
        "status": "scheduled",
        "home_score": null,
        "away_score": null,
        "elo_home": 1681.401611328125,
        "elo_away": 2003.713134765625,
        "model": {
          "home_win": 0.0877,
          "draw": 0.1453,
          "away_win": 0.767
        },
        "confidence": 0.9814,
        "n_observations": 2804
      },
      {
        "id": 68,
        "group": "L",
        "round": 3,
        "date": "2026-06-27",
        "home": "CRO",
        "away": "GHA",
        "home_name": "Croatia",
        "away_name": "Ghana",
        "status": "scheduled",
        "home_score": null,
        "away_score": null,
        "elo_home": 1926.286865234375,
        "elo_away": 1701.598388671875,
        "model": {
          "home_win": 0.5866,
          "draw": 0.2488,
          "away_win": 0.1647
        },
        "confidence": 0.9814,
        "n_observations": 2812
      }
    ],
    "K": [
      {
        "id": 23,
        "group": "K",
        "round": 1,
        "date": "2026-06-17",
        "home": "POR",
        "away": "COD",
        "home_name": "Portugal",
        "away_name": "Congo DR",
        "status": "finished",
        "home_score": 1,
        "away_score": 1,
        "elo_home": 2000.123291015625,
        "elo_away": 1691.876708984375,
        "model": null,
        "confidence": 0,
        "n_observations": 0
      },
      {
        "id": 24,
        "group": "K",
        "round": 1,
        "date": "2026-06-17",
        "home": "UZB",
        "away": "COL",
        "home_name": "Uzbekistan",
        "away_name": "Colombia",
        "status": "finished",
        "home_score": 1,
        "away_score": 3,
        "elo_home": 1597.4000244140625,
        "elo_away": 1916.5999755859375,
        "model": null,
        "confidence": 0,
        "n_observations": 0
      },
      {
        "id": 47,
        "group": "K",
        "round": 2,
        "date": "2026-06-23",
        "home": "POR",
        "away": "UZB",
        "home_name": "Portugal",
        "away_name": "Uzbekistan",
        "status": "scheduled",
        "home_score": null,
        "away_score": null,
        "elo_home": 2000.123291015625,
        "elo_away": 1597.4000244140625,
        "model": {
          "home_win": 0.7957,
          "draw": 0.1393,
          "away_win": 0.065
        },
        "confidence": 0.9839,
        "n_observations": 3471
      },
      {
        "id": 48,
        "group": "K",
        "round": 2,
        "date": "2026-06-23",
        "home": "COL",
        "away": "COD",
        "home_name": "Colombia",
        "away_name": "Congo DR",
        "status": "scheduled",
        "home_score": null,
        "away_score": null,
        "elo_home": 1916.5999755859375,
        "elo_away": 1691.876708984375,
        "model": {
          "home_win": 0.6351,
          "draw": 0.2286,
          "away_win": 0.1363
        },
        "confidence": 0.9831,
        "n_observations": 3237
      },
      {
        "id": 71,
        "group": "K",
        "round": 3,
        "date": "2026-06-27",
        "home": "COL",
        "away": "POR",
        "home_name": "Colombia",
        "away_name": "Portugal",
        "status": "scheduled",
        "home_score": null,
        "away_score": null,
        "elo_home": 1916.5999755859375,
        "elo_away": 2000.123291015625,
        "model": {
          "home_win": 0.2645,
          "draw": 0.2739,
          "away_win": 0.4616
        },
        "confidence": 0.9813,
        "n_observations": 2809
      },
      {
        "id": 72,
        "group": "K",
        "round": 3,
        "date": "2026-06-27",
        "home": "COD",
        "away": "UZB",
        "home_name": "Congo DR",
        "away_name": "Uzbekistan",
        "status": "scheduled",
        "home_score": null,
        "away_score": null,
        "elo_home": 1691.876708984375,
        "elo_away": 1597.4000244140625,
        "model": {
          "home_win": 0.4557,
          "draw": 0.2624,
          "away_win": 0.2819
        },
        "confidence": 0.9813,
        "n_observations": 2672
      }
    ]
  },
  "knockout_sims": {
    "MEX": {
      "champion": 0.0045,
      "final": 0.0167,
      "semi_final": 0.0167,
      "quarter_final": 0.0649,
      "round_of_16": 0.2248,
      "round_of_32": 0.6005
    },
    "CAN": {
      "champion": 0.0011,
      "final": 0.0045,
      "semi_final": 0.0045,
      "quarter_final": 0.0228,
      "round_of_16": 0.1046,
      "round_of_32": 0.3995
    },
    "SUI": {
      "champion": 0.0444,
      "final": 0.1003,
      "semi_final": 0.1003,
      "quarter_final": 0.2254,
      "round_of_16": 0.4905,
      "round_of_32": 0.6778
    },
    "KOR": {
      "champion": 0.004,
      "final": 0.0144,
      "semi_final": 0.0144,
      "quarter_final": 0.0539,
      "round_of_16": 0.1801,
      "round_of_32": 0.3222
    },
    "BRA": {
      "champion": 0.1559,
      "final": 0.2755,
      "semi_final": 0.2755,
      "quarter_final": 0.4788,
      "round_of_16": 0.6653,
      "round_of_32": 0.8731
    },
    "PAR": {
      "champion": 0.0002,
      "final": 0.0021,
      "semi_final": 0.0021,
      "quarter_final": 0.0109,
      "round_of_16": 0.0388,
      "round_of_32": 0.1269
    },
    "USA": {
      "champion": 0.0036,
      "final": 0.0121,
      "semi_final": 0.0121,
      "quarter_final": 0.0428,
      "round_of_16": 0.1019,
      "round_of_32": 0.4033
    },
    "MAR": {
      "champion": 0.0136,
      "final": 0.0344,
      "semi_final": 0.0344,
      "quarter_final": 0.1005,
      "round_of_16": 0.194,
      "round_of_32": 0.5967
    },
    "GER": {
      "champion": 0.0496,
      "final": 0.0965,
      "semi_final": 0.0965,
      "quarter_final": 0.1777,
      "round_of_16": 0.3613,
      "round_of_32": 0.6659
    },
    "SWE": {
      "champion": 0.0078,
      "final": 0.0192,
      "semi_final": 0.0192,
      "quarter_final": 0.0472,
      "round_of_16": 0.1323,
      "round_of_32": 0.3341
    },
    "NED": {
      "champion": 0.0657,
      "final": 0.1311,
      "semi_final": 0.1311,
      "quarter_final": 0.2314,
      "round_of_16": 0.435,
      "round_of_32": 0.7609
    },
    "ECU": {
      "champion": 0.0015,
      "final": 0.0062,
      "semi_final": 0.0062,
      "quarter_final": 0.0213,
      "round_of_16": 0.0714,
      "round_of_32": 0.2391
    },
    "BEL": {
      "champion": 0.0216,
      "final": 0.0522,
      "semi_final": 0.0522,
      "quarter_final": 0.112,
      "round_of_16": 0.2446,
      "round_of_32": 0.5718
    },
    "URU": {
      "champion": 0.0084,
      "final": 0.0244,
      "semi_final": 0.0244,
      "quarter_final": 0.0574,
      "round_of_16": 0.1451,
      "round_of_32": 0.4282
    },
    "ESP": {
      "champion": 0.116,
      "final": 0.2042,
      "semi_final": 0.2042,
      "quarter_final": 0.3316,
      "round_of_16": 0.5387,
      "round_of_32": 0.7932
    },
    "IRN": {
      "champion": 0.0017,
      "final": 0.0062,
      "semi_final": 0.0062,
      "quarter_final": 0.0214,
      "round_of_16": 0.0716,
      "round_of_32": 0.2068
    },
    "FRA": {
      "champion": 0.0587,
      "final": 0.1116,
      "semi_final": 0.1116,
      "quarter_final": 0.1484,
      "round_of_16": 0.2738,
      "round_of_32": 0.6895
    },
    "AUT": {
      "champion": 0.0049,
      "final": 0.0153,
      "semi_final": 0.0153,
      "quarter_final": 0.0272,
      "round_of_16": 0.071,
      "round_of_32": 0.3105
    },
    "ARG": {
      "champion": 0.2372,
      "final": 0.3402,
      "semi_final": 0.3402,
      "quarter_final": 0.4016,
      "round_of_16": 0.5556,
      "round_of_32": 0.7756
    },
    "NOR": {
      "champion": 0.0132,
      "final": 0.0292,
      "semi_final": 0.0292,
      "quarter_final": 0.0453,
      "round_of_16": 0.0996,
      "round_of_32": 0.2244
    },
    "POR": {
      "champion": 0.0452,
      "final": 0.0939,
      "semi_final": 0.0939,
      "quarter_final": 0.1322,
      "round_of_16": 0.3243,
      "round_of_32": 0.6026
    },
    "CRO": {
      "champion": 0.0138,
      "final": 0.0373,
      "semi_final": 0.0373,
      "quarter_final": 0.0587,
      "round_of_16": 0.1813,
      "round_of_32": 0.3974
    },
    "ENG": {
      "champion": 0.05,
      "final": 0.105,
      "semi_final": 0.105,
      "quarter_final": 0.1423,
      "round_of_16": 0.3418,
      "round_of_32": 0.6261
    },
    "COL": {
      "champion": 0.0099,
      "final": 0.028,
      "semi_final": 0.028,
      "quarter_final": 0.0443,
      "round_of_16": 0.1526,
      "round_of_32": 0.3739
    },
    "SCO": {
      "champion": 0.0107,
      "final": 0.0354,
      "semi_final": 0.0354,
      "quarter_final": 0.1449,
      "round_of_16": 0.2613,
      "round_of_32": 0.4599
    },
    "JPN": {
      "champion": 0.0185,
      "final": 0.0567,
      "semi_final": 0.0567,
      "quarter_final": 0.2033,
      "round_of_16": 0.3236,
      "round_of_32": 0.5401
    },
    "EGY": {
      "champion": 0.001,
      "final": 0.0058,
      "semi_final": 0.0058,
      "quarter_final": 0.0421,
      "round_of_16": 0.1036,
      "round_of_32": 0.3382
    },
    "CZE": {
      "champion": 0.011,
      "final": 0.045,
      "semi_final": 0.045,
      "quarter_final": 0.1716,
      "round_of_16": 0.3115,
      "round_of_32": 0.6618
    },
    "COD": {
      "champion": 0.0008,
      "final": 0.0055,
      "semi_final": 0.0055,
      "quarter_final": 0.0424,
      "round_of_16": 0.1363,
      "round_of_32": 0.4255
    },
    "CIV": {
      "champion": 0.0024,
      "final": 0.0139,
      "semi_final": 0.0139,
      "quarter_final": 0.0796,
      "round_of_16": 0.2207,
      "round_of_32": 0.5745
    },
    "SEN": {
      "champion": 0.0198,
      "final": 0.0615,
      "semi_final": 0.0615,
      "quarter_final": 0.2281,
      "round_of_16": 0.4278,
      "round_of_32": 0.6267
    },
    "ALG": {
      "champion": 0.0033,
      "final": 0.0157,
      "semi_final": 0.0157,
      "quarter_final": 0.088,
      "round_of_16": 0.2152,
      "round_of_32": 0.3733
    }
  },
  "value_board": []
}